geomexp/__init__.py
geomexp/ml.py
geomexp/images/__init__.py
geomexp/images/baldwin/__init__.py
geomexp/images/baldwin/bw_exp_s.png
geomexp/images/baldwin/bw_exp_s1.5-1.png
geomexp/images/baldwin/bw_exp_s1.5.png
geomexp/images/baldwin/bw_exp_s2-1.png
geomexp/images/baldwin/bw_exp_s2.5-1.png
geomexp/images/baldwin/bw_exp_s2.5.png
geomexp/images/baldwin/bw_exp_s2.png
geomexp/images/baldwin/bw_exp_s3-1.png
geomexp/images/baldwin/bw_exp_s3.4.png
geomexp/images/baldwin/bw_exp_s3.5-1.png
geomexp/images/baldwin/bw_exp_s3.png
geomexp/images/baldwin/bw_exp_s4-1.png
geomexp/images/baldwin/bw_sim_s1-1.5.png
geomexp/images/baldwin/bw_sim_s1-2.0.png
geomexp/images/baldwin/bw_sim_s1-2.5.png
geomexp/images/baldwin/bw_sim_s1-3.0.png
geomexp/images/baldwin/bw_sim_s1-3.5.png
geomexp/images/baldwin/bw_sim_s1.0.png
geomexp/images/baldwin/bw_sim_s1.5.png
geomexp/images/baldwin/bw_sim_s2.0.png
geomexp/images/baldwin/bw_sim_s2.5.png
geomexp/images/baldwin/bw_sim_s3.4.png
geomexp/images/baldwin/bw_sim_s3.png
geomexp/images/ml/__init__.py
geomexp/images/ml/ml_exp_10.png
geomexp/images/ml/ml_exp_100.png
geomexp/images/ml/ml_exp_110.png
geomexp/images/ml/ml_exp_120.png
geomexp/images/ml/ml_exp_130.png
geomexp/images/ml/ml_exp_140.png
geomexp/images/ml/ml_exp_150.png
geomexp/images/ml/ml_exp_160.png
geomexp/images/ml/ml_exp_170.png
geomexp/images/ml/ml_exp_20.png
geomexp/images/ml/ml_exp_30.png
geomexp/images/ml/ml_exp_40.png
geomexp/images/ml/ml_exp_50.png
geomexp/images/ml/ml_exp_60.png
geomexp/images/ml/ml_exp_70.png
geomexp/images/ml/ml_exp_80.png
geomexp/images/ml/ml_exp_90.png
geomexp-0.2.1.dist-info/LICENSE
geomexp-0.2.1.dist-info/METADATA
geomexp-0.2.1.dist-info/WHEEL
geomexp-0.2.1.dist-info/top_level.txt
geomexp-0.2.1.dist-info/RECORD
